LICENSE
README.md
setup.py
CVE_2022_21500.egg-info/PKG-INFO
CVE_2022_21500.egg-info/SOURCES.txt
CVE_2022_21500.egg-info/dependency_links.txt
CVE_2022_21500.egg-info/entry_points.txt
CVE_2022_21500.egg-info/requires.txt
CVE_2022_21500.egg-info/top_level.txt
cve202221500/main.py
cve202221500/includes/__init__.py
cve202221500/includes/bot.py
cve202221500/includes/filereader.py
cve202221500/includes/scan.py
cve202221500/includes/writefile.py
cve202221500/utils/__init__.py
cve202221500/utils/configure.py
cve202221500/utils/const.py
cve202221500/utils/helpers.py
cve202221500/utils/status.py